{
  "id": "mDWJfRTTKmL",
  "version": 1,
  "recordings": {
    "tAGoXi0o2Rz": {
      "id": "tAGoXi0o2Rz",
      "value": {
        "name": "Netherlands"
      }
    },
    "6doNpsjpadn": {
      "id": "6doNpsjpadn",
      "value": {
        "name": "Chicago"
      }
    },
    "mA1xdMRkYN2": {
      "id": "mA1xdMRkYN2",
      "value": {
        "name": "Poland"
      }
    },
    "1RKEcIGyjOw": {
      "id": "1RKEcIGyjOw",
      "value": {
        "name": "Japan"
      }
    },
    "irMJzj3I88G": {
      "id": "irMJzj3I88G",
      "value": {
        "name": "Ann Arbor"
      }
    },
    "qsahcOUVjhM": {
      "id": "qsahcOUVjhM",
      "value": {
        "name": "Netherlands"
      }
    },
    "ot4bIKqElu3": {
      "id": "ot4bIKqElu3",
      "value": {
        "name": "Finland"
      }
    },
    "2aHhudHvvTt": {
      "id": "2aHhudHvvTt",
      "value": {
        "name": "Sydney"
      }
    },
    "uxtOIA-Xcfe": {
      "id": "uxtOIA-Xcfe",
      "value": {
        "name": "Ardea"
      }
    },
    "w8RTvxpSpvK": {
      "id": "w8RTvxpSpvK",
      "value": {
        "name": "Saint-Jean-sur-Richelieu"
      }
    }
  }
}